<{* 解答一覧用XML *}>
<?xml version="1.0" encoding="<{$smarty.const._CHARSET}>"?>
<{strip}>
<lists>
	<{foreach from=$action.summaries item=summary}>
		<row>
			<{if $action.chiefItemShow}>
				<answer_user>
					<![CDATA[
						<{include file = "quiz_view_handle.html" handle=$summary.insert_user_name|smarty:nodefaults user_id=$summary.insert_user_id}>
					]]>
				</answer_user>
			<{/if}>
			
			<answer_number>
				<{$lang.quiz_number|sprintf:$summary.answer_number}>
			</answer_number>
			
			<answer_time>
				<{$summary.answer_time|timezone_date_format:$lang._full_date_format}>
			</answer_time>
			
			<summary_score>
				<{$lang.quiz_point_allocation|sprintf:$summary.summary_score:$action.quiz.perfect_score}>
			</summary_score>
			
			<deviation>
				<{$lang.quiz_deviation_value|sprintf:$summary.deviation}>
			</deviation>
			
			<manage>
				<![CDATA[
					<{include file = "quiz_view_answer_link.html"}>
				]]>
			</manage>
		</row>
	<{/foreach}>
</lists>
<{/strip}>